Workbook

Sheet Dashboard
B2: DASHBOARD — APURAÇÃO PIS/COFINS
B3: Comercial Exemplo LTDA | Competência 07/2026 | Regime cumulativo
N4: Categoria | O4: Valor
B5: Receita Bruta Total | D5: Receita Excluída | F5: Base de Cálculo | H5: Total a Recolher | N5: Receita Tributada | O5: =Apuração!B11 -> 3337000
B6: =Apuração!B13 -> 3997000 | D6: =Apuração!B12 -> 660000 | F6: =Apuração!B21 -> 3337000 | H6: =Apuração!D27 -> 121800.5 | N6: Receita Excluída | O6: =Apuração!B12 -> 660000
N7: Despesa Dedutível | O7: =Apuração!B16 -> 1535000
B8: PIS a Pagar | D8: COFINS a Pagar | F8: Despesa Dedutível | H8: Nº de Inconsistências | N8: Despesa Não Dedutível | O8: =Apuração!B18 -> 703000
B9: =Apuração!D25 -> 21690.5 | D9: =Apuração!D26 -> 100110 | F9: =Apuração!B16 -> 1535000 | H9: 4
N11: Tributo | O11: Débito | P11: Crédito | Q11: A Pagar
N12: PIS | O12: =Apuração!B25 -> 21690.5 | P12: =Apuração!C25 -> 0 | Q12: =Apuração!D25 -> 21690.5
N13: COFINS | O13: =Apuração!B26 -> 100110 | P13: =Apuração!C26 -> 0 | Q13: =Apuração!D26 -> 100110

Sheet Apuração
A1: APURAÇÃO DE PIS E COFINS
A2: Empresa: Comercial Exemplo LTDA
A3: CNPJ: 12.345.678/0001-90 | Competência: 07/2026 | Regime: cumulativo
A5: PARÂMETROS (editáveis)
A6: Alíquota PIS | B6: 0.0065
A7: Alíquota COFINS | B7: 0.03
A8: Permite crédito (1=sim, 0=não) | B8: 0
A10: COMPOSIÇÃO DA RECEITA
A11: Receita Tributada | B11: =SUMIFS('Balancete Classificado'!$E$2:$E$28,'Balancete Classificado'!$K$2:$K$28,"RECEITA_TRIBUTADA") -> 3337000
A12: (+) Receita Excluída | B12: =SUMIFS('Balancete Classificado'!$E$2:$E$28,'Balancete Classificado'!$K$2:$K$28,"RECEITA_EXCLUIDA") -> 660000
A13: (=) Receita Bruta Total | B13: =B11+B12 -> 3997000
A15: DESPESAS
A16: Despesa Dedutível (base potencial de crédito) | B16: =SUMIFS('Balancete Classificado'!$E$2:$E$28,'Balancete Classificado'!$K$2:$K$28,"DESPESA_DEDUTIVEL") -> 1535000
A17: Despesa Dedutível que GERA crédito | B17: =SUMIFS('Balancete Classificado'!$E$2:$E$28,'Balancete Classificado'!$K$2:$K$28,"DESPESA_DEDUTIVEL",'Balancete Classificado'!$H$2:$H$28,"Sim") -> 1535000
A18: Despesa Não Dedutível | B18: =SUMIFS('Balancete Classificado'!$E$2:$E$28,'Balancete Classificado'!$K$2:$K$28,"DESPESA_NAO_DEDUTIVEL") -> 703000
A20: BASE DE CÁLCULO
A21: Base de Cálculo (Receita Tributada) | B21: =B11 -> 3337000
A23: APURAÇÃO DOS TRIBUTOS
A24: Tributo | B24: Débito | C24: Crédito | D24: A Pagar
A25: PIS | B25: =B21*$B$6 -> 21690.5 | C25: =B17*$B$6*$B$8 -> 0 | D25: =MAX(B25-C25,0) -> 21690.5
A26: COFINS | B26: =B21*$B$7 -> 100110 | C26: =B17*$B$7*$B$8 -> 0 | D26: =MAX(B26-C26,0) -> 100110
A27: TOTAL | B27: =SUM(B25:B26) -> 121800.5 | C27: =SUM(C25:C26) -> 0 | D27: =SUM(D25:D26) -> 121800.5

Sheet Balancete Classificado
A1: Conta | B1: Descrição | C1: Natureza | D1: Classificação | E1: Valor Apuração | F1: CST PIS | G1: CST COFINS | H1: Gera Crédito | I1: Origem | J1: Confiança | K1: Chave
A2: 3.1.1.001 | B2: Receita de Venda de Mercadorias | C2: RECEITA | D2: Receita Tributada | E2: 2500000 | F2: 1.0 | G2: 1.0 | H2: Não | I2: cadastro | J2: alta | K2: RECEITA_TRIBUTADA
A3: 3.1.1.002 | B3: Receita de Prestação de Serviços | C3: RECEITA | D3: Receita Tributada | E3: 800000 | F3: 1.0 | G3: 1.0 | H3: Não | I3: cadastro | J3: alta | K3: RECEITA_TRIBUTADA
A4: 3.1.1.003 | B4: Receita de Exportação de Mercadorias | C4: RECEITA | D4: Receita Excluída | E4: 400000 | F4: 8.0 | G4: 8.0 | H4: Não | I4: cadastro | J4: alta | K4: RECEITA_EXCLUIDA
A5: 3.1.2.001 | B5: Vendas Canceladas | C5: RECEITA | D5: Receita Excluída | E5: 60000 | F5: 1.0 | G5: 1.0 | H5: Não | I5: cadastro | J5: alta | K5: RECEITA_EXCLUIDA
A6: 3.1.2.002 | B6: Descontos Incondicionais Concedidos | C6: RECEITA | D6: Receita Excluída | E6: 45000 | F6: 1.0 | G6: 1.0 | H6: Não | I6: cadastro | J6: alta | K6: RECEITA_EXCLUIDA
A7: 3.1.3.001 | B7: IPI sobre Vendas | C7: RECEITA | D7: Receita Excluída | E7: 90000 | F7: 1.0 | G7: 1.0 | H7: Não | I7: cadastro | J7: alta | K7: RECEITA_EXCLUIDA
A8: 3.1.3.002 | B8: ICMS Substituição Tributária | C8: RECEITA | D8: Receita Excluída | E8: 30000 | F8: 1.0 | G8: 1.0 | H8: Não | I8: cadastro | J8: alta | K8: RECEITA_EXCLUIDA
A9: 3.2.1.001 | B9: Receita Financeira - Juros Ativos | C9: RECEITA | D9: Receita Tributada | E9: 25000 | F9: 1.0 | G9: 1.0 | H9: Não | I9: cadastro | J9: alta | K9: RECEITA_TRIBUTADA
A10: 3.2.2.001 | B10: Reversão de Provisões | C10: RECEITA | D10: Receita Excluída | E10: 15000 | F10: 8.0 | G10: 8.0 | H10: Não | I10: cadastro | J10: alta | K10: RECEITA_EXCLUIDA
A11: 3.2.3.001 | B11: Receita de Venda de Imobilizado | C11: RECEITA | D11: Receita Excluída | E11: 20000 | F11: 06 | G11: 06 | H11: Não | I11: palavra-chave | J11: media | K11: RECEITA_EXCLUIDA
A12: 3.9.9.001 | B12: Outras Receitas Operacionais | C12: RECEITA | D12: Receita Tributada | E12: 12000 | F12: 01 | G12: 01 | H12: Não | I12: palavra-chave | J12: media | K12: RECEITA_TRIBUTADA
A13: 4.1.1.001 | B13: Compra de Mercadoria para Revenda | C13: DESPESA | D13: Despesa Dedutível (gera crédito) | E13: 900000 | F13: 50.0 | G13: 50.0 | H13: Sim | I13: cadastro | J13: alta | K13: DESPESA_DEDUTIVEL
... A27: 2.3.1.001 | B27: Capital Social | C27: PATRIMONIAL | D27: Não Classificada / Fora da Apuração | E27: 1000000 | F27: nan | G27: nan | H27: Não | I27: cadastro | J27: alta | K27: NAO_CLASSIFICADA
D28: TOTAL | E28: =SUM(E2:E27) -> 7535000

Sheet Log de Inconsistências
A1: # | B1: Conta | C1: Descrição | D1: Valor | E1: Tipo | F1: Detalhe | G1: Severidade | H1: Ação Sugerida
A2: 1 | B2: 4.2.4.001 | C2: Despesas com Viagens | D2: 22000 | E2: Conta ausente no cadastro | F2: Não cadastrada. Classificação automática: Despesa Não Dedutível (origem: prefixo, confiança: baixa). Regra: Conta inicia com prefixo de despesa ('4',) (assumida NÃO dedutível por segurança) | G2: Alta | H2: Incluir a conta no cadastro Cofins com a classificação correta.
A3: 2 | B3: 4.9.9.001 | C3: Outras Despesas Diversas | D3: 18000 | E3: Conta ausente no cadastro | F3: Não cadastrada. Classificação automática: Despesa Não Dedutível (origem: prefixo, confiança: baixa). Regra: Conta inicia com prefixo de despesa ('4',) (assumida NÃO dedutível por segurança) | G3: Alta | H3: Incluir a conta no cadastro Cofins com a classificação correta.
A4: 3 | B4: 3.2.3.001 | C4: Receita de Venda de Imobilizado | D4: 20000 | E4: Conta ausente no cadastro | F4: Não cadastrada. Classificação automática: Receita Excluída (origem: palavra-chave, confiança: media). Regra: Descrição contém 'venda de imobilizado' | G4: Média | H4: Incluir a conta no cadastro Cofins com a classificação correta.
A5: 4 | B5: 3.9.9.001 | C5: Outras Receitas Operacionais | D5: 12000 | E5: Conta ausente no cadastro | F5: Não cadastrada. Classificação automática: Receita Tributada (origem: palavra-chave, confiança: media). Regra: Descrição contém 'receita' | G5: Média | H5: Incluir a conta no cadastro Cofins com a classificação correta.

Sheet Auditoria Tributária
A1: AUDITORIA TRIBUTÁRIA — TRILHA DE DECISÃO
A2: Rastreabilidade de cada conta: como foi classificada, com que confiança e sua contribuição para os tributos.
A4: Conta | B4: Descrição | C4: Classificação | D4: Origem | E4: Confiança | F4: Regra Aplicada | G4: Valor | H4: CST PIS | I4: CST COFINS | J4: Base de Crédito | K4: PIS (linha) | L4: COFINS (linha)
A5: 3.1.1.001 | B5: Receita de Venda de Mercadorias | C5: Receita Tributada | D5: cadastro | E5: alta | F5: Classificação obtida diretamente do cadastro Cofins. | G5: 2500000 | H5: 1.0 | I5: 1.0 | J5: 0 | K5: 16250 | L5: 75000
A6: 3.1.1.002 | B6: Receita de Prestação de Serviços | C6: Receita Tributada | D6: cadastro | E6: alta | F6: Classificação obtida diretamente do cadastro Cofins. | G6: 800000 | H6: 1.0 | I6: 1.0 | J6: 0 | K6: 5200 | L6: 24000
A7: 3.1.1.003 | B7: Receita de Exportação de Mercadorias | C7: Receita Excluída | D7: cadastro | E7: alta | F7: Classificação obtida diretamente do cadastro Cofins. | G7: 400000 | H7: 8.0 | I7: 8.0 | J7: 0 | K7: 0 | L7: 0
A8: 3.1.2.001 | B8: Vendas Canceladas | C8: Receita Excluída | D8: cadastro | E8: alta | F8: Classificação obtida diretamente do cadastro Cofins. | G8: 60000 | H8: 1.0 | I8: 1.0 | J8: 0 | K8: 0 | L8: 0
A9: 3.1.2.002 | B9: Descontos Incondicionais Concedidos | C9: Receita Excluída | D9: cadastro | E9: alta | F9: Classificação obtida diretamente do cadastro Cofins. | G9: 45000 | H9: 1.0 | I9: 1.0 | J9: 0 | K9: 0 | L9: 0
A10: 3.1.3.001 | B10: IPI sobre Vendas | C10: Receita Excluída | D10: cadastro | E10: alta | F10: Classificação obtida diretamente do cadastro Cofins. | G10: 90000 | H10: 1.0 | I10: 1.0 | J10: 0 | K10: 0 | L10: 0
A11: 3.1.3.002 | B11: ICMS Substituição Tributária | C11: Receita Excluída | D11: cadastro | E11: alta | F11: Classificação obtida diretamente do cadastro Cofins. | G11: 30000 | H11: 1.0 | I11: 1.0 | J11: 0 | K11: 0 | L11: 0
A12: 3.2.1.001 | B12: Receita Financeira - Juros Ativos | C12: Receita Tributada | D12: cadastro | E12: alta | F12: Classificação obtida diretamente do cadastro Cofins. | G12: 25000 | H12: 1.0 | I12: 1.0 | J12: 0 | K12: 162.5 | L12: 750
A13: 3.2.2.001 | B13: Reversão de Provisões | C13: Receita Excluída | D13: cadastro | E13: alta | F13: Classificação obtida diretamente do cadastro Cofins. | G13: 15000 | H13: 8.0 | I13: 8.0 | J13: 0 | K13: 0 | L13: 0
A14: 3.2.3.001 | B14: Receita de Venda de Imobilizado | C14: Receita Excluída | D14: palavra-chave | E14: media | F14: Descrição contém 'venda de imobilizado' | G14: 20000 | H14: 06 | I14: 06 | J14: 0 | K14: 0 | L14: 0
A15: 3.9.9.001 | B15: Outras Receitas Operacionais | C15: Receita Tributada | D15: palavra-chave | E15: media | F15: Descrição contém 'receita' | G15: 12000 | H15: 01 | I15: 01 | J15: 0 | K15: 78 | L15: 360
A16: 4.1.1.001 | B16: Compra de Mercadoria para Revenda | C16: Despesa Dedutível (gera crédito) | D16: cadastro | E16: alta | F16: Classificação obtida diretamente do cadastro Cofins. | G16: 900000 | H16: 50.0 | I16: 50.0 | J16: 0 | K16: 0 | L16: 0
... A30: 2.3.1.001 | B30: Capital Social | C30: Não Classificada / Fora da Apuração | D30: cadastro | E30: alta | F30: Classificação obtida diretamente do cadastro Cofins. | G30: 1000000 | H30: nan | I30: nan | J30: 0 | K30: 0 | L30: 0
F31: TOTAIS | G31: =SUM(G5:G30) -> 7535000 | J31: =SUM(J5:J30) -> 0 | K31: =SUM(K5:K30) -> 21690.5 | L31: =SUM(L5:L30) -> 100110
